{
  "1/6": [
    "La Befana"
  ],
  "1/17": [
    "Sant'Antonio Abate"
  ],
  "2/3": [
    "San Biagio"
  ],
  "3/8": [
    "Festa della Donna"
  ],
  "3/19": [
    "Festa del Papà"
  ],
  "4/1": [
    "Pesce d'aprile"
  ],
  "4/21": [
    "Natale di Roma"
  ],
  "4/25": [
    "Festa del Bocolo (Venezia)"
  ],
  "5/22": [
    "Santa Rita da Cascia"
  ],
  "7/2": [
    "Palio di Siena (Provenzano)"
  ],
  "8/10": [
    "Notte di San Lorenzo"
  ],
  "8/16": [
    "Palio di Siena (Assunta)"
  ],
  "11/11": [
    "Estate di San Martino"
  ]
}
